azure/__init__.py
azure/ml/__init__.py
azure/ml/api/__init__.py
azure/ml/api/batch/__init__.py
azure/ml/api/batch/_batch_sdk_utilities.py
azure/ml/api/batch/batch_decorators.py
azure/ml/api/batch/batch_handler.py
azure/ml/api/exceptions/BadRequest.py
azure/ml/api/exceptions/InternalServerError.py
azure/ml/api/exceptions/NotFound.py
azure/ml/api/exceptions/ServiceUnavailable.py
azure/ml/api/exceptions/TooManyRequests.py
azure/ml/api/exceptions/Unauthorized.py
azure/ml/api/exceptions/UnsupportedMediaType.py
azure/ml/api/exceptions/__init__.py
azure/ml/api/realtime/__init__.py
azure/ml/api/realtime/services.py
azure/ml/api/schema/__init__.py
azure/ml/api/schema/common.py
azure/ml/api/schema/dataTypes.py
azure/ml/api/schema/dtypeToSwagger.py
azure/ml/api/schema/numpyutil.py
azure/ml/api/schema/pandasutil.py
azure/ml/api/schema/sampleDefinition.py
azure/ml/api/schema/schemaObjects.py
azure/ml/api/schema/schemautil.py
azure/ml/api/schema/sparkToSwagger.py
azure/ml/api/schema/sparkutil.py
azure_ml_api_sdk-0.1.0a11.dist-info/DESCRIPTION.rst
azure_ml_api_sdk-0.1.0a11.dist-info/METADATA
azure_ml_api_sdk-0.1.0a11.dist-info/RECORD
azure_ml_api_sdk-0.1.0a11.dist-info/WHEEL
azure_ml_api_sdk-0.1.0a11.dist-info/metadata.json
azure_ml_api_sdk-0.1.0a11.dist-info/top_level.txt
azureml/__init__.py
azureml/api/__init__.py
azureml/api/batch/__init__.py
azureml/api/batch/_batch_sdk_utilities.py
azureml/api/batch/batch_handler.py
azureml/api/exceptions/ApiException.py
azureml/api/exceptions/BadRequest.py
azureml/api/exceptions/ClientSideException.py
azureml/api/exceptions/InternalServerError.py
azureml/api/exceptions/NotFound.py
azureml/api/exceptions/ServerSideException.py
azureml/api/exceptions/ServiceUnavailable.py
azureml/api/exceptions/TooManyRequests.py
azureml/api/exceptions/Unauthorized.py
azureml/api/exceptions/UnsupportedMediaType.py
azureml/api/exceptions/__init__.py
azureml/api/realtime/__init__.py
azureml/api/realtime/services.py
azureml/api/realtime/swagger_spec_generator.py
azureml/api/realtime/templates/main_template.txt
azureml/api/realtime/templates/swagger_template.json
azureml/api/schema/__init__.py
azureml/api/schema/baseUtil.py
azureml/api/schema/constants.py
azureml/api/schema/dataTypes.py
