Metadata-Version: 2.0
Name: azure-ml-api-sdk
Version: 0.1.0a11
Summary: Microsoft Azure Machine Learning Python SDK for authoring web services
Home-page: https://github.com/Azure/azure-ml-api-sdk-python
Author: Microsoft Corporation
Author-email: deployml@microsoft.com
License: MIT
Keywords: azure machinelearning model operationalization
Platform: UNKNOWN
Classifier: Development Status :: 3 - Alpha
Classifier: Intended Audience :: Developers
Classifier: Intended Audience :: System Administrators
Classifier: License :: OSI Approved :: MIT License
Classifier: Programming Language :: Python
Classifier: Programming Language :: Python :: 2
Classifier: Programming Language :: Python :: 2.7
Classifier: Programming Language :: Python :: 3
Classifier: Programming Language :: Python :: 3.5
Classifier: Topic :: Software Development :: Libraries :: Application Frameworks
Classifier: Topic :: Software Development :: Libraries :: Python Modules
Requires-Dist: liac-arff
Requires-Dist: python-dateutil
Requires-Dist: pytz
